osqp/ext_builtin.cpython-312-darwin.so
osqp/codegen/codegen_src/Makefile
osqp/codegen/codegen_src/inc/public/osqp.h
osqp/codegen/codegen_src/inc/public/osqp_export_define.h
osqp/codegen/codegen_src/inc/public/osqp_api_types.h
osqp/codegen/codegen_src/inc/public/osqp_api_constants.h
osqp/codegen/codegen_src/inc/public/osqp_api_functions.h
osqp/codegen/codegen_src/inc/private/error.h
osqp/codegen/codegen_src/inc/private/qdldl_types.h
osqp/codegen/codegen_src/inc/private/version.h
osqp/codegen/codegen_src/inc/private/qdldl_version.h
osqp/codegen/codegen_src/inc/private/algebra_vector.h
osqp/codegen/codegen_src/inc/private/types.h
osqp/codegen/codegen_src/inc/private/qdldl.h
osqp/codegen/codegen_src/inc/private/kkt.h
osqp/codegen/codegen_src/inc/private/timing.h
osqp/codegen/codegen_src/inc/private/algebra_impl.h
osqp/codegen/codegen_src/inc/private/lin_alg.h
osqp/codegen/codegen_src/inc/private/scaling.h
osqp/codegen/codegen_src/inc/private/algebra_matrix.h
osqp/codegen/codegen_src/inc/private/profilers.h
osqp/codegen/codegen_src/inc/private/qdldl_interface.h
osqp/codegen/codegen_src/inc/private/util.h
osqp/codegen/codegen_src/inc/private/csc_math.h
osqp/codegen/codegen_src/inc/private/glob_opts.h
osqp/codegen/codegen_src/inc/private/csc_utils.h
osqp/codegen/codegen_src/inc/private/printing.h
osqp/codegen/codegen_src/inc/private/auxil.h
osqp/codegen/codegen_src/src/util.c
osqp/codegen/codegen_src/src/qdldl_interface.c
osqp/codegen/codegen_src/src/csc_utils.c
osqp/codegen/codegen_src/src/vector.c
osqp/codegen/codegen_src/src/algebra_libs.c
osqp/codegen/codegen_src/src/csc_math.c
osqp/codegen/codegen_src/src/auxil.c
osqp/codegen/codegen_src/src/osqp_api.c
osqp/codegen/codegen_src/src/error.c
osqp/codegen/codegen_src/src/kkt.c
osqp/codegen/codegen_src/src/qdldl.c
osqp/codegen/codegen_src/src/scaling.c
osqp/codegen/codegen_src/src/matrix.c
vineetb_osqp-0.0.6.dist-info/RECORD
vineetb_osqp-0.0.6.dist-info/WHEEL
vineetb_osqp-0.0.6.dist-info/METADATA
vineetb_osqp-0.0.6.dist-info/licenses/LICENSE
