Metadata-Version: 2.1
Name: vineetb-osqp
Version: 0.0.6
Summary: OSQP: The Operator Splitting QP Solver
Author: Goran Banjac
Author-Email: Bartolomeo Stellato <bartolomeo.stellato@gmail.com>, Vineet Bansal <vineetbansal@protonmail.com>, Amit Solomon <as3993@princeton.edu>, Henry Schreiner <HenrySchreinerIII@gmail.com>
Project-URL: Homepage, https://osqp.org/
Requires-Python: >=3.8
Requires-Dist: jinja2
Requires-Dist: numpy>=1.7
Requires-Dist: scipy>=0.13.2
Requires-Dist: setuptools
Requires-Dist: joblib
Provides-Extra: mkl
Requires-Dist: vineetb-osqp-mkl; extra == "mkl"
Provides-Extra: dev
Requires-Dist: pre-commit; extra == "dev"
Requires-Dist: pytest>=6; extra == "dev"
Requires-Dist: torch; extra == "dev"
Requires-Dist: scipy!=1.12.0; extra == "dev"
Provides-Extra: cu12
Requires-Dist: vineetb-osqp-cu12; extra == "cu12"
